zephyrus_sc2_parser/__init__.py
zephyrus_sc2_parser/dataclasses.py
zephyrus_sc2_parser/exceptions.py
zephyrus_sc2_parser/parser.py
zephyrus_sc2_parser/requirements.txt
zephyrus_sc2_parser/utils.py
zephyrus_sc2_parser/events/__init__.py
zephyrus_sc2_parser/events/ability_event.py
zephyrus_sc2_parser/events/base_event.py
zephyrus_sc2_parser/events/camera_event.py
zephyrus_sc2_parser/events/control_group_event.py
zephyrus_sc2_parser/events/object_event.py
zephyrus_sc2_parser/events/player_leave_event.py
zephyrus_sc2_parser/events/player_stats_event.py
zephyrus_sc2_parser/events/selection_event.py
zephyrus_sc2_parser/events/upgrade_event.py
zephyrus_sc2_parser/game/__init__.py
zephyrus_sc2_parser/game/game.py
zephyrus_sc2_parser/game/game_obj.py
zephyrus_sc2_parser/game/perception_action_cycle.py
zephyrus_sc2_parser/game/player.py
zephyrus_sc2_parser/game/player_state.py
zephyrus_sc2_parser/gamedata/__init__.py
zephyrus_sc2_parser/gamedata/map_info.py
zephyrus_sc2_parser/gamedata/15405/__init__.py
zephyrus_sc2_parser/gamedata/15405/ability_data.py
zephyrus_sc2_parser/gamedata/15405/building_data.py
zephyrus_sc2_parser/gamedata/15405/unit_data.py
zephyrus_sc2_parser/gamedata/15405/upgrade_data.py
zephyrus_sc2_parser/gamedata/16561/__init__.py
zephyrus_sc2_parser/gamedata/16561/ability_data.py
zephyrus_sc2_parser/gamedata/16561/building_data.py
zephyrus_sc2_parser/gamedata/16561/unit_data.py
zephyrus_sc2_parser/gamedata/16561/upgrade_data.py
zephyrus_sc2_parser/gamedata/16605/__init__.py
zephyrus_sc2_parser/gamedata/16605/ability_data.py
zephyrus_sc2_parser/gamedata/16605/building_data.py
zephyrus_sc2_parser/gamedata/16605/unit_data.py
zephyrus_sc2_parser/gamedata/16605/upgrade_data.py
zephyrus_sc2_parser/gamedata/16755/__init__.py
zephyrus_sc2_parser/gamedata/16755/ability_data.py
zephyrus_sc2_parser/gamedata/16755/building_data.py
zephyrus_sc2_parser/gamedata/16755/unit_data.py
zephyrus_sc2_parser/gamedata/16755/upgrade_data.py
zephyrus_sc2_parser-0.3.8.dist-info/LICENSE
zephyrus_sc2_parser-0.3.8.dist-info/METADATA
zephyrus_sc2_parser-0.3.8.dist-info/WHEEL
zephyrus_sc2_parser-0.3.8.dist-info/entry_points.txt
zephyrus_sc2_parser-0.3.8.dist-info/top_level.txt
zephyrus_sc2_parser-0.3.8.dist-info/RECORD
