Metadata-Version: 2.1
Name: zephyrus-sc2-parser
Version: 0.3.8
Summary: Parser for SC2 replay files
Author-email: Luke Holroyd <hello@zephyrus.gg>
Maintainer-email: Luke Holroyd <hello@zephyrus.gg>
License: MIT License
Project-URL: homepage, https://pypi.org/project/zephyrus-sc2-parser/
Project-URL: repository, https://github.com/ZephyrBlu/zephyrus-sc2-parser
Project-URL: documentation, https://github.com/ZephyrBlu/zephyrus-sc2-parser
Classifier: Programming Language :: Python :: 3
Classifier: License :: OSI Approved :: MIT License
Classifier: Operating System :: OS Independent
Classifier: Topic :: Games/Entertainment :: Real Time Strategy
Requires-Python: >=3.8
License-File: LICENSE
Requires-Dist: requests
Requires-Dist: mpyq
Requires-Dist: pytz
